py_entity1/__init__.py
py_entity1/connection.py
tests/__init__.py
tests/test_db.py
py_entity1-1.0.0.dist-info/METADATA
py_entity1-1.0.0.dist-info/WHEEL
py_entity1-1.0.0.dist-info/top_level.txt
py_entity1-1.0.0.dist-info/RECORD
