Metadata-Version: 2.1
Name: py-entity1
Version: 1.0.0
Summary: DB Connector
Home-page: 
Author: Nikunj
Author-email: savaliyanikunj2@gmail.com
License: MIT
